vcsc_data_common/__init__.py
vcsc_data_common/ai_framework/__init__.py
vcsc_data_common/ai_framework/interval_fetching.py
vcsc_data_common/backtest/__init__.py
vcsc_data_common/fiin_data/__init__.py
vcsc_data_common/live_price_data/__init__.py
vcsc_data_common/offline_price_data/__init__.py
vcsc_data_common/oneday_portfolio/__init__.py
vcsc_data_common/order/__init__.py
vcsc_data_common/portfolio_info/__init__.py
vcsc_data_common/proprietary_trading/__init__.py
vcsc_data_common/signals/__init__.py
vcsc_data_common-0.2.5.dist-info/METADATA
vcsc_data_common-0.2.5.dist-info/WHEEL
vcsc_data_common-0.2.5.dist-info/top_level.txt
vcsc_data_common-0.2.5.dist-info/RECORD
