Metadata-Version: 2.1
Name: vcsc-data-common
Version: 0.2.5
Summary: My package description
Author: Bao Phan
Author-email: bao.phan@vcsc.com.vn
License: BSD 3-Clause License
Keywords: one,two
Classifier: Programming Language :: Python :: 3
Requires-Python: >=3.7
Requires-Dist: setuptools >=42
Requires-Dist: wheel
Requires-Dist: pandas ==1.4.1
Requires-Dist: requests
Requires-Dist: numpy
Requires-Dist: deltalake ==0.7.0
Requires-Dist: pyarrow ==11.0.0
Requires-Dist: boto3 ==1.24.59
Requires-Dist: sqlalchemy ==1.4.27
Requires-Dist: psycopg2-binary ==2.9.3
